{"version":1,"resource":"vscode-remote://wsl%2Bubuntu-24.04/home/naasir/naasir-cfi/classroom/Operators/o7.js","entries":[{"id":"mUOW.js","timestamp":1730346126578},{"id":"iaQn.js","timestamp":1730346330308},{"id":"Wijd.js","timestamp":1730346398138},{"id":"68E5.js","timestamp":1730346446028},{"id":"DAaT.js","timestamp":1730346506858},{"id":"DJJ4.js","timestamp":1730346547368},{"id":"bWRl.js","timestamp":1730346564858},{"id":"iohv.js","timestamp":1730346673018},{"id":"TK3t.js","timestamp":1730346695388},{"id":"SKUX.js","timestamp":1730346738448},{"id":"GuZ6.js","timestamp":1730346764298},{"id":"ya6j.js","timestamp":1730346878998},{"id":"RTRg.js","timestamp":1730346895538},{"id":"7aSz.js","timestamp":1730346946868},{"id":"21Qu.js","timestamp":1730346972188},{"id":"uFcu.js","timestamp":1730347086508},{"id":"3UDF.js","timestamp":1730347148798},{"id":"v8Vb.js","timestamp":1730347615208},{"id":"fGU1.js","timestamp":1730347649448},{"id":"WS4r.js","timestamp":1730347674868},{"id":"kHYs.js","timestamp":1730347732638},{"id":"1FGE.js","timestamp":1730430331159}]}